outlib/__init__.py
outlib/models.py
outlib/outcli.py
outlierpack_NG-0.1.0.dist-info/METADATA
outlierpack_NG-0.1.0.dist-info/WHEEL
outlierpack_NG-0.1.0.dist-info/entry_points.txt
outlierpack_NG-0.1.0.dist-info/top_level.txt
outlierpack_NG-0.1.0.dist-info/RECORD
