Metadata-Version: 2.1
Name: outlierpack-NG
Version: 0.1.0
Summary: Removing outliers from a pandas dataframe
Home-page: https://github.com/CachingNik/OutlierPack
Author: Nikhil Gupta
Author-email: ngupta_be17@thapar.edu
License: UNKNOWN
Keywords: CLI,OUTLIER,Data,outlier removal
Platform: UNKNOWN
Requires-Python: >=2.7
